Workbook

Sheet Raw Data
A1: Month | B1: Department | C1: Employee | D1: Target | E1: Actual | F1: Revenue | G1: Orders | H1: Expenses | I1: Customers
A2: 46023 | B2: Sales | C2: Aarav | D2: 301958 | E2: 331736 | F2: 331736 | G2: 32 | H2: 217512 | I2: 32
A3: 46023 | B3: Sales | C3: Meera | D3: 234886 | E3: 225099 | F3: 225099 | G3: 40 | H3: 111185 | I3: 35
A4: 46023 | B4: Sales | C4: Rohan | D4: 306324 | E4: 312587 | F4: 312587 | G4: 41 | H4: 198871 | I4: 13
A5: 46023 | B5: Sales | C5: Priya | D5: 239735 | E5: 266819 | F5: 266819 | G5: 55 | H5: 128122 | I5: 32
A6: 46023 | B6: Procurement | C6: Ananya | D6: 394176 | E6: 355427 | F6: 199004 | G6: 61 | H6: 96623 | I6: 38
A7: 46023 | B7: Procurement | C7: Karan | D7: 336730 | E7: 316507 | F7: 116685 | G7: 33 | H7: 62527 | I7: 14
A8: 46023 | B8: Procurement | C8: Neha | D8: 249092 | E8: 254825 | F8: 106570 | G8: 56 | H8: 51492 | I8: 36
A9: 46023 | B9: Operations | C9: Vivek | D9: 419931 | E9: 422163 | F9: 212840 | G9: 43 | H9: 107152 | I9: 31
A10: 46023 | B10: Operations | C10: Ishita | D10: 300174 | E10: 316174 | F10: 187806 | G10: 25 | H10: 91696 | I10: 25
A11: 46023 | B11: Operations | C11: Rahul | D11: 215920 | E11: 190767 | F11: 117323 | G11: 19 | H11: 68286 | I11: 15
A12: 46023 | B12: Service | C12: Aditya | D12: 351829 | E12: 278833 | F12: 191534 | G12: 61 | H12: 135123 | I12: 47
A13: 46023 | B13: Service | C13: Kavya | D13: 343678 | E13: 394799 | F13: 152154 | G13: 40 | H13: 92053 | I13: 32
... A118: 46266 | B118: Service | C118: Nikhil | D118: 257709 | E118: 273592 | F118: 119063 | G118: 55 | H118: 74788 | I118: 45

Sheet Calculations
A1: Month | B1: Department | C1: Employee | D1: Target | E1: Actual | F1: Revenue | G1: Orders | H1: Expenses | I1: Customers | J1: Achievement % | K1: Profit | L1: Profit Margin % | M1: Performance
A2: ='Raw Data'!A2 | B2: ='Raw Data'!B2 | C2: ='Raw Data'!C2 | D2: ='Raw Data'!D2 | E2: ='Raw Data'!E2 | F2: ='Raw Data'!F2 | G2: ='Raw Data'!G2 | H2: ='Raw Data'!H2 | I2: ='Raw Data'!I2 | J2: =IFERROR(E2/D2,0) | K2: =F2-H2 | L2: =IFERROR(K2/F2,0) | M2: =IF(J2>=1,"Achieved","Below Target")
A3: ='Raw Data'!A3 | B3: ='Raw Data'!B3 | C3: ='Raw Data'!C3 | D3: ='Raw Data'!D3 | E3: ='Raw Data'!E3 | F3: ='Raw Data'!F3 | G3: ='Raw Data'!G3 | H3: ='Raw Data'!H3 | I3: ='Raw Data'!I3 | J3: =IFERROR(E3/D3,0) | K3: =F3-H3 | L3: =IFERROR(K3/F3,0) | M3: =IF(J3>=1,"Achieved","Below Target")
A4: ='Raw Data'!A4 | B4: ='Raw Data'!B4 | C4: ='Raw Data'!C4 | D4: ='Raw Data'!D4 | E4: ='Raw Data'!E4 | F4: ='Raw Data'!F4 | G4: ='Raw Data'!G4 | H4: ='Raw Data'!H4 | I4: ='Raw Data'!I4 | J4: =IFERROR(E4/D4,0) | K4: =F4-H4 | L4: =IFERROR(K4/F4,0) | M4: =IF(J4>=1,"Achieved","Below Target")
A5: ='Raw Data'!A5 | B5: ='Raw Data'!B5 | C5: ='Raw Data'!C5 | D5: ='Raw Data'!D5 | E5: ='Raw Data'!E5 | F5: ='Raw Data'!F5 | G5: ='Raw Data'!G5 | H5: ='Raw Data'!H5 | I5: ='Raw Data'!I5 | J5: =IFERROR(E5/D5,0) | K5: =F5-H5 | L5: =IFERROR(K5/F5,0) | M5: =IF(J5>=1,"Achieved","Below Target")
A6: ='Raw Data'!A6 | B6: ='Raw Data'!B6 | C6: ='Raw Data'!C6 | D6: ='Raw Data'!D6 | E6: ='Raw Data'!E6 | F6: ='Raw Data'!F6 | G6: ='Raw Data'!G6 | H6: ='Raw Data'!H6 | I6: ='Raw Data'!I6 | J6: =IFERROR(E6/D6,0) | K6: =F6-H6 | L6: =IFERROR(K6/F6,0) | M6: =IF(J6>=1,"Achieved","Below Target")
A7: ='Raw Data'!A7 | B7: ='Raw Data'!B7 | C7: ='Raw Data'!C7 | D7: ='Raw Data'!D7 | E7: ='Raw Data'!E7 | F7: ='Raw Data'!F7 | G7: ='Raw Data'!G7 | H7: ='Raw Data'!H7 | I7: ='Raw Data'!I7 | J7: =IFERROR(E7/D7,0) | K7: =F7-H7 | L7: =IFERROR(K7/F7,0) | M7: =IF(J7>=1,"Achieved","Below Target")
A8: ='Raw Data'!A8 | B8: ='Raw Data'!B8 | C8: ='Raw Data'!C8 | D8: ='Raw Data'!D8 | E8: ='Raw Data'!E8 | F8: ='Raw Data'!F8 | G8: ='Raw Data'!G8 | H8: ='Raw Data'!H8 | I8: ='Raw Data'!I8 | J8: =IFERROR(E8/D8,0) | K8: =F8-H8 | L8: =IFERROR(K8/F8,0) | M8: =IF(J8>=1,"Achieved","Below Target")
A9: ='Raw Data'!A9 | B9: ='Raw Data'!B9 | C9: ='Raw Data'!C9 | D9: ='Raw Data'!D9 | E9: ='Raw Data'!E9 | F9: ='Raw Data'!F9 | G9: ='Raw Data'!G9 | H9: ='Raw Data'!H9 | I9: ='Raw Data'!I9 | J9: =IFERROR(E9/D9,0) | K9: =F9-H9 | L9: =IFERROR(K9/F9,0) | M9: =IF(J9>=1,"Achieved","Below Target")
A10: ='Raw Data'!A10 | B10: ='Raw Data'!B10 | C10: ='Raw Data'!C10 | D10: ='Raw Data'!D10 | E10: ='Raw Data'!E10 | F10: ='Raw Data'!F10 | G10: ='Raw Data'!G10 | H10: ='Raw Data'!H10 | I10: ='Raw Data'!I10 | J10: =IFERROR(E10/D10,0) | K10: =F10-H10 | L10: =IFERROR(K10/F10,0) | M10: =IF(J10>=1,"Achieved","Below Target")
A11: ='Raw Data'!A11 | B11: ='Raw Data'!B11 | C11: ='Raw Data'!C11 | D11: ='Raw Data'!D11 | E11: ='Raw Data'!E11 | F11: ='Raw Data'!F11 | G11: ='Raw Data'!G11 | H11: ='Raw Data'!H11 | I11: ='Raw Data'!I11 | J11: =IFERROR(E11/D11,0) | K11: =F11-H11 | L11: =IFERROR(K11/F11,0) | M11: =IF(J11>=1,"Achieved","Below Target")
A12: ='Raw Data'!A12 | B12: ='Raw Data'!B12 | C12: ='Raw Data'!C12 | D12: ='Raw Data'!D12 | E12: ='Raw Data'!E12 | F12: ='Raw Data'!F12 | G12: ='Raw Data'!G12 | H12: ='Raw Data'!H12 | I12: ='Raw Data'!I12 | J12: =IFERROR(E12/D12,0) | K12: =F12-H12 | L12: =IFERROR(K12/F12,0) | M12: =IF(J12>=1,"Achieved","Below Target")
A13: ='Raw Data'!A13 | B13: ='Raw Data'!B13 | C13: ='Raw Data'!C13 | D13: ='Raw Data'!D13 | E13: ='Raw Data'!E13 | F13: ='Raw Data'!F13 | G13: ='Raw Data'!G13 | H13: ='Raw Data'!H13 | I13: ='Raw Data'!I13 | J13: =IFERROR(E13/D13,0) | K13: =F13-H13 | L13: =IFERROR(K13/F13,0) | M13: =IF(J13>=1,"Achieved","Below Target")
... A118: ='Raw Data'!A118 | B118: ='Raw Data'!B118 | C118: ='Raw Data'!C118 | D118: ='Raw Data'!D118 | E118: ='Raw Data'!E118 | F118: ='Raw Data'!F118 | G118: ='Raw Data'!G118 | H118: ='Raw Data'!H118 | I118: ='Raw Data'!I118 | J118: =IFERROR(E118/D118,0) | K118: =F118-H118 | L118: =IFERROR(K118/F118,0) | M118: =IF(J118>=1,"Achieved","Below Target")

Sheet Dashboard
B2: MONTHLY MIS DASHBOARD
B4: Total Revenue | D4: Total Orders | F4: Target Achievement
B5: =SUM(Calculations!F:F) | D5: =SUM(Calculations!G:G) | F5: =IFERROR(SUM(Calculations!E:E)/SUM(Calculations!D:D),0)
B7: Total Expenses | D7: Total Profit | F7: Profit Margin
B8: =SUM(Calculations!H:H) | D8: =SUM(Calculations!K:K) | F8: =IFERROR(SUM(Calculations!K:K)/SUM(Calculations!F:F),0)
B11: Month | C11: Revenue | D11: Expenses | E11: Profit | F11: Orders | G11: Achievement %
B12: 46023 | C12: =SUMIFS(Calculations!F:F,Calculations!A:A,B12) | D12: =SUMIFS(Calculations!H:H,Calculations!A:A,B12) | E12: =C12-D12 | F12: =SUMIFS(Calculations!G:G,Calculations!A:A,B12) | G12: =IFERROR(SUMIFS(Calculations!E:E,Calculations!A:A,B12)/SUMIFS(Calculations!D:D,Calculations!A:A,B12),0)
B13: 46054 | C13: =SUMIFS(Calculations!F:F,Calculations!A:A,B13) | D13: =SUMIFS(Calculations!H:H,Calculations!A:A,B13) | E13: =C13-D13 | F13: =SUMIFS(Calculations!G:G,Calculations!A:A,B13) | G13: =IFERROR(SUMIFS(Calculations!E:E,Calculations!A:A,B13)/SUMIFS(Calculations!D:D,Calculations!A:A,B13),0)
B14: 46082 | C14: =SUMIFS(Calculations!F:F,Calculations!A:A,B14) | D14: =SUMIFS(Calculations!H:H,Calculations!A:A,B14) | E14: =C14-D14 | F14: =SUMIFS(Calculations!G:G,Calculations!A:A,B14) | G14: =IFERROR(SUMIFS(Calculations!E:E,Calculations!A:A,B14)/SUMIFS(Calculations!D:D,Calculations!A:A,B14),0)
B15: 46113 | C15: =SUMIFS(Calculations!F:F,Calculations!A:A,B15) | D15: =SUMIFS(Calculations!H:H,Calculations!A:A,B15) | E15: =C15-D15 | F15: =SUMIFS(Calculations!G:G,Calculations!A:A,B15) | G15: =IFERROR(SUMIFS(Calculations!E:E,Calculations!A:A,B15)/SUMIFS(Calculations!D:D,Calculations!A:A,B15),0)
B16: 46143 | C16: =SUMIFS(Calculations!F:F,Calculations!A:A,B16) | D16: =SUMIFS(Calculations!H:H,Calculations!A:A,B16) | E16: =C16-D16 | F16: =SUMIFS(Calculations!G:G,Calculations!A:A,B16) | G16: =IFERROR(SUMIFS(Calculations!E:E,Calculations!A:A,B16)/SUMIFS(Calculations!D:D,Calculations!A:A,B16),0)
B17: 46174 | C17: =SUMIFS(Calculations!F:F,Calculations!A:A,B17) | D17: =SUMIFS(Calculations!H:H,Calculations!A:A,B17) | E17: =C17-D17 | F17: =SUMIFS(Calculations!G:G,Calculations!A:A,B17) | G17: =IFERROR(SUMIFS(Calculations!E:E,Calculations!A:A,B17)/SUMIFS(Calculations!D:D,Calculations!A:A,B17),0)
B18: 46204 | C18: =SUMIFS(Calculations!F:F,Calculations!A:A,B18) | D18: =SUMIFS(Calculations!H:H,Calculations!A:A,B18) | E18: =C18-D18 | F18: =SUMIFS(Calculations!G:G,Calculations!A:A,B18) | G18: =IFERROR(SUMIFS(Calculations!E:E,Calculations!A:A,B18)/SUMIFS(Calculations!D:D,Calculations!A:A,B18),0)
B19: 46235 | C19: =SUMIFS(Calculations!F:F,Calculations!A:A,B19) | D19: =SUMIFS(Calculations!H:H,Calculations!A:A,B19) | E19: =C19-D19 | F19: =SUMIFS(Calculations!G:G,Calculations!A:A,B19) | G19: =IFERROR(SUMIFS(Calculations!E:E,Calculations!A:A,B19)/SUMIFS(Calculations!D:D,Calculations!A:A,B19),0)
B20: 46266 | C20: =SUMIFS(Calculations!F:F,Calculations!A:A,B20) | D20: =SUMIFS(Calculations!H:H,Calculations!A:A,B20) | E20: =C20-D20 | F20: =SUMIFS(Calculations!G:G,Calculations!A:A,B20) | G20: =IFERROR(SUMIFS(Calculations!E:E,Calculations!A:A,B20)/SUMIFS(Calculations!D:D,Calculations!A:A,B20),0)
B22: Department | C22: Revenue | D22: Orders | E22: Achievement %
B23: Sales | C23: =SUMIFS(Calculations!F:F,Calculations!B:B,B23) | D23: =SUMIFS(Calculations!G:G,Calculations!B:B,B23) | E23: =IFERROR(SUMIFS(Calculations!E:E,Calculations!B:B,B23)/SUMIFS(Calculations!D:D,Calculations!B:B,B23),0)
B24: Procurement | C24: =SUMIFS(Calculations!F:F,Calculations!B:B,B24) | D24: =SUMIFS(Calculations!G:G,Calculations!B:B,B24) | E24: =IFERROR(SUMIFS(Calculations!E:E,Calculations!B:B,B24)/SUMIFS(Calculations!D:D,Calculations!B:B,B24),0)
B25: Operations | C25: =SUMIFS(Calculations!F:F,Calculations!B:B,B25) | D25: =SUMIFS(Calculations!G:G,Calculations!B:B,B25) | E25: =IFERROR(SUMIFS(Calculations!E:E,Calculations!B:B,B25)/SUMIFS(Calculations!D:D,Calculations!B:B,B25),0)
B26: Service | C26: =SUMIFS(Calculations!F:F,Calculations!B:B,B26) | D26: =SUMIFS(Calculations!G:G,Calculations!B:B,B26) | E26: =IFERROR(SUMIFS(Calculations!E:E,Calculations!B:B,B26)/SUMIFS(Calculations!D:D,Calculations!B:B,B26),0)
B28: Excel Skills Demonstrated
B29: • Data organization and cleaning
B30: • IF / IFERROR formulas
B31: • SUMIFS calculations
B32: • KPI reporting
B33: • Monthly trend analysis
B34: • Dashboard design
B35: • Charts and business reporting

Sheet Project Guide
A1: Monthly MIS Dashboard – Excel Portfolio Project
A2: Objective | B2: Analyze monthly business performance using Excel.
A3: Sheets | B3: Raw Data, Calculations, Dashboard, Project Guide
A4: Main KPIs | B4: Revenue, Orders, Target Achievement, Expenses, Profit, Profit Margin
A5: Excel Skills | B5: SUMIFS, IF, IFERROR, Pivot-style analysis, Charts, KPI reporting
A6: Note | B6: Dataset is fictional and created for portfolio/learning purposes.
